{
  "schema": "chancela-external-validator-sidecar/v1",
  "case_id": "bt-timestamped",
  "validator": {
    "family": "eu-dss",
    "name": "EU DSS validation",
    "version": null,
    "run_status": "pending_operator_run",
    "run_at": null,
    "operator": null,
    "command": null,
    "environment": null,
    "report_path": null
  },
  "document": {
    "path": "../input/bt-timestamped.pdf",
    "sha256": null,
    "bytes": null
  },
  "expected": {
    "overall_indication": "TOTAL_PASSED",
    "sub_indication": null,
    "pades_profile": "B-T",
    "signature_count": 1,
    "signature_timestamp_present": true,
    "dss_present": false,
    "doc_time_stamp_present": false,
    "tamper_detected": false
  },
  "observed": null,
  "notes": [
    "Pending operator run; expected fields are the assertion target, not a recorded validator result."
  ]
}
